{"file_id": "lines-aaa", "context": "Oh, I forgot something!", "response": "Give me the food first!", "context/0": "Bring a lot of radish?", "context/1": "Really?", "context/2": "Bring it here.", "context/3": "I ordered it.", "context/4": "I'm delivering Chinese food.", "context/5": "Come here!", "context/6": "Where you headed?", "context/7": "Hey, you!", "context/8": "These girls sure love Chinese food.", "context/9": "I'm cleverer than I look."}
{"file_id": "lines-aaa", "context": "My birthday's in two days.", "response": "You're dead if you forget.", "context/0": "Hi, Gyeon-woo.", "context/1": "Gyeon-woo: Uh?", "context/2": "Good night, dad.", "context/3": "/Gyeon-woo:", "context/4": "Go to sleep.", "context/5": "Gyeon-woo's Father:", "context/6": "Time for bed.", "context/7": "Gyeon-woo's Father: Yes, I do.", "context/8": "You don't trust me?", "context/9": "Of course not, dad."}
{"file_id": "lines-aaa", "context": "You come over here.", "response": "Didn't I say eat one a piece!", "context/0": "Hey!", "context/1": "See you.", "context/2": "Of course.", "context/3": "Don't just pass by us next time, all right?", "context/4": "Oh, yeah.", "context/5": "Uh...", "context/6": "And remember to keep in touch!", "context/7": "Bye!", "context/8": "Take care you guys!", "context/9": "You're out!"}
{"file_id": "lines-aaa", "context": "Plus, I hate when she rubs my face and kisses me.", "response": "Uncle does, too.", "context/0": "We don't look alike.", "context/1": "Still there?", "context/2": "She'll be so glad to see you.", "context/3": "She says you resemble him.", "context/4": "You know she feels lonely after losing her son last year.", "context/5": "That long?", "context/6": "It's been over a year since you saw her.", "context/7": "Make sure you pay a visit.", "context/8": "Talk over there!", "context/9": "It's my mom!"}
{"file_id": "lines-aaa", "context": "When he planted the tree, he asked me if it look the same.", "response": "He said that someone would be sad if it died, so no one should know.", "context/0": "During this spring, he planted another tree that looked the same.", "context/1": "But this young man felt sorry for it.", "context/2": "It was split into two.", "context/3": "This tree was struck dead by lightning last year.", "context/4": "There's a dead tree and a living tree, too.", "context/5": "People are dead or alive.", "context/6": "But I'm not sure.", "context/7": "Well, it looks like it changed a bit.", "context/8": "Does this tree look the same as before?", "context/9": "Look closely."}
{"file_id": "lines-aaa", "context": "Gyeon-woo:", "response": "What's the prize?", "context/0": "With the right foot, you win.", "context/1": "Left foot over the line, I win.", "context/2": "On the way, we play fun games, too.", "context/3": "It's something a man must do.", "context/4": "Gyeon-woo: I always take her home, even to Bupyung station.", "context/5": "My lipstick!", "context/6": "Wanna die?", "context/7": "Don't scribble on it.", "context/8": "Is the subway your sketch book?", "context/9": "Hey, kid."}
{"file_id": "lines-aaa", "context": "I don't date part-time construction worker", "response": "It's a full-time job!", "context/0": "I found a job, I'm no longer a beggar", "context/1": "I love you!", "context/2": "They responded!", "context/3": "See?", "context/4": "How can this happen?", "context/5": "Someone plans to jump off of the building!", "context/6": "You think we can change them?", "context/7": "Haven't eaten yet?", "context/8": "You're always like this", "context/9": "I have to go to the bathroom"}
{"file_id": "lines-aaa", "context": "Seregay, here's the photo and the address", "response": "I'm standing here!", "context/0": "You fellows think carefully about what I said", "context/1": "Show him the way out", "context/2": "Our guest is leaving", "context/3": "I'll finish him with my blade", "context/4": "Let me take care of that damn Governor-General", "context/5": "Sir!", "context/6": "Dol-Suk!", "context/7": "The Japs should be hacked to death", "context/8": "Look, you think terrorism is all about guns and knives, but that's the decent part of it", "context/9": "We have to change our society through enlightenment"}
{"file_id": "lines-aaa", "context": "A kiss...", "response": "Fuck, stop kicking my foot.", "context/0": "A kiss...", "context/1": "But my kiss of love isn't for just anyone.", "context/2": "If all Frenchmen are like you, that would surprise her.", "context/3": "If all Frenchmen are like you, there won't be that many.", "context/4": "In France, we have a lot of virgins.", "context/5": "In France, we have enough virgins like that.", "context/6": "The Virgin of the Pillar wants to be, not French but captain of the Aragonese troops.", "context/7": "Translate.", "context/8": "She wants to be the captain of the Aragonese troops.", "context/9": "The Virgin of the Pillar says that she doesn't want to be French."}
{"file_id": "lines-aaa", "context": "There he is.", "response": "What's happening over here?", "context/0": "to dream about me.", "context/1": "...to dream about me...", "context/2": "Only for you my love, only for you my love to dream about me...", "context/3": "I want to vaporize as well...", "context/4": "I want to be a white cloud...", "context/5": "For that there's a rhyme - the chicken...", "context/6": "Glass of wine and five lemonades...", "context/7": "Then there will be a gale...", "context/8": "I want to play with breeze...", "context/9": "That would make an addict of me."}
{"file_id": "lines-aaa", "context": "No' and since I can't see their faces I can't find closure and so I was stranded here and cannot leave", "response": "can you help me?", "context/0": "Can you see the faces of the 3 men?", "context/1": "So!", "context/2": "Can't you see that she is poor enough already?", "context/3": "Are you two serious?", "context/4": "Hey!", "context/5": "Rape is rape!", "context/6": "What are you talking about?", "context/7": "There were 3 people so it must be gang rape!", "context/8": "Of course it's not rape!", "context/9": "More like raped!"}
{"file_id": "lines-aaa", "context": "Nine hours and not a whisper.", "response": "Which is alright with me.", "context/0": "Coffee Colonel?", "context/1": "Condition Red!", "context/2": "Scramble all aircraft immediately!", "context/3": "Condition Red!", "context/4": "Colonel Parkman speaking...", "context/5": "Operations!", "context/6": "Yes sir!", "context/7": "Hit the alert button!", "context/8": "Well, it's because the sound of the vibration may start an avalanche.", "context/9": "You know how, mountain climbers are afraid of thunder?"}
{"file_id": "lines-aaa", "context": "The end of the railroad.", "response": "Shut up, Feeney.", "context/0": "Now what?", "context/1": "I didn't.", "context/2": "Did you bring it?", "context/3": "Not now!", "context/4": "Did you bring the payroll?", "context/5": "Before you pass.", "context/6": "Come over to the telegraph shack.", "context/7": "Mr Kimball.", "context/8": "Come on!", "context/9": "Come on!"}
{"file_id": "lines-aaa", "context": "OK, John.", "response": "Hurry it up, Jubilee!", "context/0": "Torgenson!", "context/1": "We'll pull it down.", "context/2": "Throw some ropes around them timbers.", "context/3": "Youcan'tgo anydistance in a buggy or a hack", "context/4": "Something'sgottatakeyou there and gotta bring you back", "context/5": "Youcan'tgetfar withoutarailroad", "context/6": "Oh,youcan'tget far withoutarailroad", "context/7": "AndI tootedon thewhistle and the darned thing ran", "context/8": "ThenI builtalocomotive out of 20 empty cans", "context/9": "AndI laidalittletrack along the bullfrog crick"}
{"file_id": "lines-aaa", "context": "Too good for the guy that owned it.", "response": "Remember that draw you taught me?", "context/0": "It's a pretty good rig.", "context/1": "Come on.", "context/2": "Sure.", "context/3": "Put him away, Howdy.", "context/4": "Hi, Utica.", "context/5": "I even broke with the Utica Kid.", "context/6": "No, you don't have to talk.", "context/7": "Doesn't mean I have to talk.", "context/8": "I broke with Whitey.", "context/9": "All right."}
{"file_id": "lines-aaa", "context": "That there sorrel is the horse I want.", "response": "He belongs to my friend Grant McLaine.", "context/0": "That there sorrel is the only horse what come in.", "context/1": "Don't start that too.", "context/2": "A man told you to put his horse up...", "context/3": "Barley!", "context/4": "They've cut in Mr Kimball's car.", "context/5": "It's extremely important that I see him.", "context/6": "How should I know?", "context/7": "What colour horse your man riding?", "context/8": "Ain't nobody been here but the man riding the sorrel.", "context/9": "Are you sure he didn't come while I was away?"}
{"file_id": "lines-aaa", "context": "I've eaten.", "response": "Just get coffee.", "context/0": "You haven't eaten yet?", "context/1": "Renner, go to Pete's and get one breakfast and a jug of coffee.", "context/2": "All right, Jeff.", "context/3": "Sit down.", "context/4": "Hello, Grant.", "context/5": "I certainly do.", "context/6": "You want to see me, Ben?", "context/7": "Come in.", "context/8": "Any more arguments?", "context/9": "Then you can help me sell lunches at the station."}
{"file_id": "lines-aaa", "context": "Step down.", "response": "Much obliged.", "context/0": "Howdy, ma'am.", "context/1": "Oh.", "context/2": "I think there's a few warm dregs left.", "context/3": "Howdy.", "context/4": "Too late for coffee, mister?", "context/5": "Goodbye, Mac.", "context/6": "Thanks, Tim.", "context/7": "Yeah.", "context/8": "I must have squeezed out a few wrong notes.", "context/9": "And this is the tune your father used to play to keep peace in the house?"}
{"file_id": "lines-aaa", "context": "\u266a Wherever you may be \u266a", "response": "\u266a Follow the river back to me \u266a", "context/0": "\u266a Follow the river \u266a", "context/1": "\u266a When you've an empty head \u266a", "context/2": "\u266a Does it matter how full the moon \u266a", "context/3": "\u266a And tell the sky above \u266a", "context/4": "\u266a could jump over the moon \u266a", "context/5": "\u266a Sometimes I feel like \u266a", "context/6": "Now go on.", "context/7": "We're at end of track.", "context/8": "Get a bucket and start carrying water.", "context/9": "All right, Joey."}
{"file_id": "lines-aaa", "context": "You're a big girl now.", "response": "I'm beginning to understand about that other woman too.", "context/0": "You just gotta live in it.", "context/1": "When you grow up, you realize you can't run away from the world.", "context/2": "No, I was to blame.", "context/3": "Somebody else's war is always to blame.", "context/4": "I used to blame the war for everything, didn't I?", "context/5": "The war may not be over for a long time.", "context/6": "With Mount Kenya and God in the garden.", "context/7": "I want to go home to our home.", "context/8": "At least a hundred years.", "context/9": "Let's see, about a month ago?"}
{"file_id": "lines-aaa", "context": "It was not my hands that struck them.", "response": "I believe you.", "context/0": "I did not hurt her or her children.", "context/1": "I did not hurt her.", "context/2": "Yes.", "context/3": "Peter?", "context/4": "She is with child.", "context/5": "And Memsahib Elizabeth?", "context/6": "Yes.", "context/7": "He's a friend of my father.", "context/8": "He was a good man.", "context/9": "As well as age will allow."}
{"file_id": "lines-aaa", "context": "Tomorrow, you can take Elizabeth into Nairobi.", "response": "To the hospital.", "context/0": "Where's Jeff?", "context/1": "Jeff.", "context/2": "Elizabeth.", "context/3": "Send up the flare.", "context/4": "The flare, Papa.", "context/5": "Mau Mau gangs are being forced deeper into the Aberdare Mountains.", "context/6": "Several farmers in the Nyeri District have quit their farms and returned to England.", "context/7": "The emergency operations now cost the government more than a million pounds every month.", "context/8": "You wouldn't have one chance in a thousand of coming out alive.", "context/9": "The old man says yes."}
{"file_id": "lines-aaa", "context": "Say yes before God and I'll believe you.", "response": "I've said enough.", "context/0": "Did God tell you to create Mau Mau?", "context/1": "Yes.", "context/2": "You swore to drive the white men out of Africa, didn't you?", "context/3": "Yes.", "context/4": "By force?", "context/5": "Yes.", "context/6": "Did you give the oath to others?", "context/7": "I believe you.", "context/8": "No.", "context/9": "Did you ever take the Mau Mau blood oath yourself?"}
{"file_id": "lines-aaa", "context": "If you think I'm scared...", "response": "As if I'm going to shoot you!", "context/0": "I shoot.", "context/1": "If you do not fall behind, I'll scream.", "context/2": "Fernand, be kind.", "context/3": "Send it.", "context/4": "What?", "context/5": "Fernand!", "context/6": "We thought that you're tired, because the car drove.", "context/7": "Nice to hire?", "context/8": "I also.", "context/9": "I was in a hurry."}
{"file_id": "lines-aaa", "context": "That's just an excuse.", "response": "So what if his girl's left him?", "context/0": "I know.", "context/1": "He got a bad letter from home.", "context/2": "You're not being fair.", "context/3": "You afraid that if we cure you, you might go back in the army?", "context/4": "Want to desert it?", "context/5": "You're a soldier in the Red Army!", "context/6": "Quiet down!", "context/7": "Bastards!", "context/8": "Guys, the chief is coming!", "context/9": "There're plenty of hospitals in this wide world."}
{"file_id": "lines-aaa", "context": "We can't go on living the way we did, enjoying ourselves while death stalks our land.", "response": "We will be happy some day.", "context/0": "I must go.", "context/1": "It's war!", "context/2": "But it can't be helped.", "context/3": "It's hard leaving you.", "context/4": "On this day you were born.", "context/5": "My only one, happy birthday...", "context/6": "There's a note here from somebody named Boris.", "context/7": "Look, you mustn't think that...", "context/8": "Where's my squirrel?", "context/9": "Where's the squirrel?"}
{"file_id": "lines-aaa", "context": "A harmless mental disturbance.", "response": "Grandma, why aren't you asleep?", "context/0": "That's love, my dear.", "context/1": "And he's over her.", "context/2": "She's gone crazy over him.", "context/3": "Squirrel!", "context/4": "Don't be late.", "context/5": "All right.", "context/6": "I'll be working.", "context/7": "No, I can't make it.", "context/8": "What time on Thursday?", "context/9": "Squirrel, at what time?"}
{"file_id": "lines-aaa", "context": "Go on now.", "response": "We'll say goodbye later.", "context/0": "a hundred years.", "context/1": "And after that we'll live together...", "context/2": "Do you hear?", "context/3": "I'm going to be all right.", "context/4": "I like that.", "context/5": "White cranes flying...", "context/6": "Squirrel, what is this?", "context/7": "Boris!", "context/8": "Of course.", "context/9": "And now I have to go."}
{"file_id": "lines-aaa", "context": "When Veronica is safe and you're by my side, I'm not afraid.", "response": "They're still at it, the brutes.", "context/0": "What about you?", "context/1": "She's so scared, poor girl!", "context/2": "Be careful in the subway.", "context/3": "Go now.", "context/4": "If it becomes dangerous, we'll go down to the shelter.", "context/5": "I won't go without you.", "context/6": "It's right there.", "context/7": "The backpack?", "context/8": "Where's the backpack?", "context/9": "Go get your things."}
{"file_id": "lines-aaa", "context": "Of course not.", "response": "That didn't come out right.", "context/0": "Missing doesn't mean dead.", "context/1": "Was?", "context/2": "I didn't know Boris, but everyone says he was a gifted young man.", "context/3": "From my eldest son on the Ukrainian front.", "context/4": "Nothing.", "context/5": "Palyukaitis?", "context/6": "That's me.", "context/7": "Lededeva?", "context/8": "For you.", "context/9": "There's nothing for you."}
{"file_id": "lines-aaa", "context": "What kind of trick is this?", "response": "What trick?", "context/0": "What's this?", "context/1": "Why, I think it's quite clear.", "context/2": "Interesting, but unintelligible.", "context/3": "\"The symptoms of such compound fractures depend on the degree of changes in the joints, as well as on the location.\"", "context/4": "You are a kind man after all, Mark Alexandrovich.", "context/5": "A little boy is having a birthday and I wanted to give him a present.", "context/6": "Thank you, Anna.", "context/7": "Here.", "context/8": "He is now.", "context/9": "Is Mark here?"}
{"file_id": "lines-aaa", "context": "And I'm taking the boy...", "response": "Perhaps someone else had better rent a room?", "context/0": "I'm going to rent a room.", "context/1": "It's all right.", "context/2": "What are you doing, Veronica?", "context/3": "Tell us how you got this exemption.", "context/4": "You know I've got an exemption, Uncle Fedya.", "context/5": "And you owe nothing to no one?", "context/6": "Or do you believe that for your petty pleasures and well-being others must lose their arms, legs, eyes, jaws, even their lives?", "context/7": "What do you mean?", "context/8": "Do you believe that anybody likes having his son marching off to war?", "context/9": "Shut the door."}
{"file_id": "lines-aaa", "context": "Hello, Nadia", "response": "You're more beautiful than your picture", "context/0": "I only want you to be happy, Daddy", "context/1": "Just a plain congratulation?", "context/2": "Congratulations", "context/3": "If you love her, Nadia, I will love her", "context/4": "You should love her", "context/5": "I am sure you'll love her", "context/6": "The only condition in the woman I was going to marry was that she would take care of you, and I found her", "context/7": "And now I married for your sake too", "context/8": "I have lived without marriage for 14 years, for your sake", "context/9": "Yes, Nadia"}
{"file_id": "lines-aaa", "context": "Please forgive me", "response": "I can't handle your music or philosophy today!", "context/0": "Oh, God, O Mighty Avenger", "context/1": "God, has Your revenge started to take effect?", "context/2": "I sold out the innocent woman to buy a criminal instead!", "context/3": "I drove the loyal wife away from his life and put a cheat in her place", "context/4": "No, it's a whole bottle of whiskey, don't be late", "context/5": "I'll try to come put I won't stay for long, just for a little while", "context/6": "Okay", "context/7": "You go, and next week we'll spend a whole day with her", "context/8": "You wouldn't go yesterday, she'll be disappointed", "context/9": "Darling, you know I have to go to the farm with the lawyer to close the deal and sell it"}
{"file_id": "lines-aaa", "context": "And it always will be us.", "response": "Don't think of the past, sweetheart.", "context/0": "It's always been us.", "context/1": "It's never been you or me.", "context/2": "We're a team, aren't we?", "context/3": "You had nothing to do with it.", "context/4": "Where'd you get this \"our\" business?", "context/5": "Wait a minute.", "context/6": "You make it sound like a virtue... as if it were our Christian duty to kill anyone that gets in our way.", "context/7": "It's got to be that way.", "context/8": "You come first.", "context/9": "The first thing they teach you in the Marine Corps is to cover yourself."}
{"file_id": "lines-aaa", "context": "It'll get us out of here.", "response": "We don't need him anymore.", "context/0": "What does that get us?", "context/1": "Put it on his pack so he'll find it when he gets back.", "context/2": "Nardo, get the $10,000.", "context/3": "I'll pay him off, I'll tell him about us... and that's all there'll be to it.", "context/4": "I meant when we get across the border.", "context/5": "But you said \"get rid of him.\"", "context/6": "As far as I can see, I never should have.", "context/7": "I've got nothing against Cameron.", "context/8": "I don't go out looking for trouble.", "context/9": "I'm no gun-crazy killer."}
{"file_id": "lines-aaa", "context": "Why'd you do it, Meg?", "response": "Because something's happened to you, Nardo.", "context/0": "We've got a good two days' hike to cross over.", "context/1": "She's never been here before.", "context/2": "How would she know?", "context/3": "Is that what she told you?", "context/4": "Why do you look at her?", "context/5": "Five miles?", "context/6": "I thought about five miles.", "context/7": "How close to the border you think we are?", "context/8": "I'll be on my way.", "context/9": "Why don't we go on across the border?"}
{"file_id": "lines-aaa", "context": "When she came and saw all the cinemas and stuff, she was hooked.", "response": "It's like that, with country girls.", "context/0": "Her uncle had lodgings at the Bastille.", "context/1": "You know how it is.", "context/2": "She's changed her mind?", "context/3": "Then there was my wife, Paris meant nothing to her.", "context/4": "I wasn't qualified for the civil service.", "context/5": "Me neither.", "context/6": "I couldn't get a job on the subway.", "context/7": "I tried other things", "context/8": "No...", "context/9": "Did you join the force straight away?"}
{"file_id": "lines-aaa", "context": "None of us ever know the answer to that question until the moment arises.", "response": "What's your opinion, Shears?", "context/0": "well, at Ieast he was honest.", "context/1": "You see what I mean.", "context/2": "We'II let you know.", "context/3": "Am I to go with the team?", "context/4": "Thank you, Joyce.", "context/5": "well, I think that's all.", "context/6": "It's an old army problem.", "context/7": "I suppose I find it hard to kid myself that killing isn't a crime.", "context/8": "I've tried to imagine myself....", "context/9": "I don't honestly know, sir."}
{"file_id": "lines-aaa", "context": "Has Clipton seen you?", "response": "Just about to.", "context/0": "Then there were some who just got tired of living.", "context/1": "Famine, overwork, bullet wounds, snakebites Saito.", "context/2": "Other causes of death:", "context/3": "They died of malaria, dysentery, beri-beri, gangrene.", "context/4": "And what happened to them?", "context/5": "Indians, Burmese, Siamese.", "context/6": "Some British.", "context/7": "Some lime", "context/8": "Mostly Aussies.", "context/9": "And your group here?"}
{"file_id": "lines-aaa", "context": "It goes without saying that I'm proud of all of you.", "response": "But we're facing a crisis.", "context/0": "Look here, men.", "context/1": "Good man.", "context/2": "I'll try, sir.", "context/3": "Nothing difficult.", "context/4": "You?", "context/5": "Good show.", "context/6": "Anything you say, sir.", "context/7": "Do you feel up to doing a little light work on the bridge?", "context/8": "Stand easy, Baker.", "context/9": "Trimmings and finishing jobs."}
{"file_id": "lines-aaa", "context": "Once that happens, I've got it made.", "response": "Got it what?", "context/0": "\"Ship him home for impersonating an officer.\"", "context/1": "When the Navy learns the truth, they'll say:", "context/2": "You want an officer an American Commander Shears who doesn't exist.", "context/3": "The point is, you can't use me.", "context/4": "That's the whole story.", "context/5": "I saw one of them on the beach.", "context/6": "There were certain advantages.", "context/7": "I kind of got used to being a commander so when I arrived at the hospital I took a look at the enlisted men's ward and then the officer's ward and I said to myself, \" Let's let it ride along for a while.\"", "context/8": "There's always the unexpected, isn't there?", "context/9": "But with Saito, the officers worked along with the rest."}
{"file_id": "lines-aaa", "context": "Reeves, carry on.", "response": "Yes, sir.", "context/0": "All the work up to now has been quite useless.", "context/1": "Mud.", "context/2": "Major Reeves, our engineer, has made a careful study of the site... and has come to the conclusion that the river bottom there is too soft.", "context/3": "Unfortunately, yes.", "context/4": "We feel the position of the bridge was fixed rather hastily... and incorrectly.", "context/5": "The next point is somewhat unpleasant for all concerned.", "context/6": "Oh, yes.", "context/7": "Now", "context/8": "I think that takes care of all the procedural matters.", "context/9": "We must draw up our plans... then arrange a conference with Saito... and set him straight."}
{"file_id": "lines-aaa", "context": "I'll be forced to close the hospital... and your patients will work in their place.", "response": "Many will die, and he will be responsible.", "context/0": "Tell him that if his officers will not work...", "context/1": "Thank you.", "context/2": "I have decided to allow you one visit to your colonel.", "context/3": "Sit down, please.", "context/4": "Quite mad.", "context/5": "Your colonel is mad.", "context/6": "This is not a game of cricket.", "context/7": "This is war!", "context/8": "Do not speak to me of rules!", "context/9": "As he pointed out, it's against the rules."}
{"file_id": "lines-aaa", "context": "Stand easy.", "response": "We're gonna be a busy pair of gravediggers, Weaver.", "context/0": "Into line, left turn.", "context/1": "Halt.", "context/2": "Mark time!", "context/3": "\"A\" Company, mark time!", "context/4": "He found little enough of it while he was alive.", "context/5": "May he rest in peace.", "context/6": "I don't mock the grave or the man.", "context/7": "No need to mock the grave.", "context/8": "Come off it.", "context/9": "What did he die for?"}
{"file_id": "lines-aaa", "context": "Too much talk always spoils it.", "response": "What's wrong with that thing?", "context/0": "No, that would spoil it.", "context/1": "I'll teach you to say that in Siamese.", "context/2": "What's a nice girl like you doing in a place like this?", "context/3": "She'll take the leeches off your back.", "context/4": "She's telling you to hold still.", "context/5": "Leeches.", "context/6": "Leeches.", "context/7": "Yes, sir.", "context/8": "Be happy in your work.", "context/9": "Lovely."}
{"file_id": "lines-aaa", "context": "It should be interesting.", "response": "Col. Green's given me the Kwai bridge.", "context/0": "I don't want to discourage...", "context/1": "You see, none of us have ever been there.", "context/2": "Our chief problem is lack of firsthand knowledge.", "context/3": "With demolition equipment through that jungle?", "context/4": "Parachute drop, then march.", "context/5": "How?", "context/6": "We'll have to go smash it on the ground.", "context/7": "It's too far for bombers to carry a load.", "context/8": "We'll try to prevent them.", "context/9": "The Japanese aim to open the Bangkok- Rangoon section by the middle of May."}
{"file_id": "lines-aaa", "context": "Have you ever constructed a bridge across a stream like the Kwai?", "response": "Yes, sir.", "context/0": "Yes, sir?", "context/1": "Reeves.", "context/2": "Yes, sir.", "context/3": "We must put a stop to these demonstrations.", "context/4": "No, sir.", "context/5": "It may be funny, and I'm sure it's done with the best motives... but it's not military behavior.", "context/6": "If not, stop making those faces.", "context/7": "Have you a nervous affliction?", "context/8": "Yes, sir.", "context/9": "A corporal should always know exactly how many men he has under him."}
{"file_id": "lines-aaa", "context": "I see what you mean.", "response": "You don't see what I mean at all!", "context/0": "Also the kind they had in 1 91 4, when your officers went over the top... with nothing but a swagger stick.", "context/1": "That kind of guts.", "context/2": "How's that, sir?", "context/3": "Into the valley of death rode the 600.", "context/4": "He's got guts.", "context/5": "I'll say this for the old man:", "context/6": "You see, there are certain advantages to being on the sick list.", "context/7": "Is this your soldier's code, murdering unarmed men?", "context/8": "Shut up!", "context/9": "Most of those men can't walk."}
{"file_id": "lines-aaa", "context": "Here again I know the men.", "response": "It's essential that they take pride in their job.", "context/0": "But it's going to be a proper bridge.", "context/1": "So we're lucky.", "context/2": "That we would, sir.", "context/3": "If there weren't any work, we'd invent some.", "context/4": "You've got to keep them occupied.", "context/5": "I know our men.", "context/6": "You're not usually so slow in the uptake.", "context/7": "You really want them to build the bridge?", "context/8": "I beg your pardon, sir.", "context/9": "There's the challenge."}
{"file_id": "lines-aaa", "context": "He's been shut up in that hut", "response": "I could have you shot.", "context/0": "It's about Colonel Nicholson.", "context/1": "I've been trying to see you for three days.", "context/2": "You wish to see me?", "context/3": "Let go!", "context/4": "No, no, no!", "context/5": "One, two, three, four.", "context/6": "Timber!", "context/7": "And so say all of us", "context/8": "For he's a jolly good fellow", "context/9": "For he's a jolly good fellow For he's a jolly good fellow"}
{"file_id": "lines-aaa", "context": "Kill him!", "response": "Kill him!", "context/0": "You don't understand, sir!", "context/1": "Let me go, sir!", "context/2": "Kill him!", "context/3": "Kill him!", "context/4": "Help!", "context/5": "Help!", "context/6": "No, no!", "context/7": "There's no time!", "context/8": "Yes, sir.", "context/9": "Blow up the bridge?"}
{"file_id": "lines-aaa", "context": "We'll swing north through heavy jungle.", "response": "Then who's going to lead?", "context/0": "There are too many Japanese patrols.", "context/1": "Yai says we can't reach the Kwai your way.", "context/2": "He's in the trees!", "context/3": "With or without!", "context/4": "Oh, very good!", "context/5": "With or without parachute?", "context/6": "The consensus is, the most sensible thing for Shears to do is to go ahead and jump and hope for the best.", "context/7": "Three jumps, you're bound to get your packet.", "context/8": "Two jumps, 80%.", "context/9": "If you make one jump there's only a 50% chance of injury."}
{"file_id": "lines-aaa", "context": "I taught Oriental languages at Cambridge before the war.", "response": "I never congratulated you on your escape.", "context/0": "Do you read this?", "context/1": "Very good, sir.", "context/2": "Pot of tea for one, please, Peter.", "context/3": "No, thank you.", "context/4": "A drink?", "context/5": "No, thanks.", "context/6": "Would you care for one?", "context/7": "Oh, I'm dying for a cup of tea.", "context/8": "Go ahead.", "context/9": "This is my place."}
{"file_id": "lines-aaa", "context": "Take this bridge of yours.", "response": "It's quite an enormous undertaking.", "context/0": "Now.", "context/1": "Good.", "context/2": "Of course.", "context/3": "Tell me, colonel do you agree that the first job of an officer is command?", "context/4": "Now.", "context/5": "Please sit down.", "context/6": "I'm sure we can arrive at a solution.", "context/7": "That won't solve your problem.", "context/8": "Clipton did mention that.", "context/9": "Do you understand?"}
{"file_id": "lines-aaa", "context": "He's been in isolation too long, poor chap.", "response": "Cut off from his unit.", "context/0": "Even for an Ameri", "context/1": "Queer bird.", "context/2": "A living slave.", "context/3": "As for me, I'm just a slave.", "context/4": "I hope they can remain soldiers, colonel.", "context/5": "Are you with me there, commander?", "context/6": "So long as they have that idea, they'll be soldiers and not slaves.", "context/7": "Our men must always feel they are still commanded by us and not by the Japanese.", "context/8": "And remember this:", "context/9": "I want everything to go off smoothly starting tomorrow morning."}
{"file_id": "lines-aaa", "context": "Yai will take three women to help you.", "response": "One will stay here with me.", "context/0": "Yai.", "context/1": "They're sure to have sentries on the bridge so you'll have to float the stuff down from upriver which means building a raft.", "context/2": "Right, you'll start as soon as it's dark.", "context/3": "Any questions?", "context/4": "All clear?", "context/5": "Perhaps I might even take a few potshots at the train.", "context/6": "On the theory that there's always one more thing I'll set up the mortar here to create an additional diversion.", "context/7": "Yai will be with you so you can occupy the Nips if they make trouble for Joyce.", "context/8": "Shears, pick a spot on our side of the bank where you can cover Joyce.", "context/9": "Thank you."}
{"file_id": "lines-aaa", "context": "l was referring to the nurse.", "response": "Oh, yes, very ingenious.", "context/0": "Sir?", "context/1": "You were in need of medical attention?", "context/2": "Four minutes late, to be exact.", "context/3": "I'm awfully sorry l'm late, sir.", "context/4": "Now get him with your boot!", "context/5": "Get on with your jobs!", "context/6": "What on earth are you people staring at?", "context/7": "Good morning.", "context/8": "Get your boot in there, will you?", "context/9": "Use your boot!"}
{"file_id": "lines-aaa", "context": "AND I TAKE IT WE ALL AGREE THAT, IF WE'RE TO AVOID DISASTER,", "response": "WE BUILD A NEW BRIDGE AT THE SITE SELECTED BY MAJOR REEVES, 400 YARDS DOWNSTREAM.", "context/0": "COLONEL, DO YOU SUPPOSE WE COULD HAVE A CUP OF TEA ?", "context/1": "JUST A MOMENT, REEVES, BEFORE YOU GET TOO INVOLVED.", "context/2": "PRESSURE AND SOIL RESISTANCE FIGURES IN TONS PER SQUARE INCH.", "context/3": "LOOK, IT'S ALL HERE.", "context/4": "THAT BRIDGE WOULD COLLAPSE UNDER THE FIRST TRAIN TO CROSS IT.", "context/5": "AND THOSE PILES OF YOURS COULD BE HAMMERED BELOW WATER LEVEL BEFORE THEY'D HOLD.", "context/6": "COLONEL SAITO, I'VE MADE TESTS,", "context/7": "YES, SIR.", "context/8": "REEVES, WILL YOU CARRY ON ?", "context/9": "ALL THE WORK UP TO NOW HAS BEEN QUITE USELESS."}
{"file_id": "lines-aaa", "context": "As for me, I'm just a slave.", "response": "A living slave.", "context/0": "I hope they can remain soldiers, colonel.", "context/1": "Are you with me there, commander?", "context/2": "So long as they have that idea, they'II be soldiers and not slaves.", "context/3": "Our men must always feel they are still commanded by us and not by the Japanese.", "context/4": "And remember this:", "context/5": "I want everything to go off smoothly starting tomorrow morning.", "context/6": "I think we're clear on the program.", "context/7": "Is there anything else?", "context/8": "I suggest we drop the subject of escape.", "context/9": "Then we have the opportunity to introduce it."}
{"file_id": "lines-aaa", "context": "Our side of the river is obviously used by the Japanese.", "response": "They'd spot it at once.", "context/0": "The problem is where to hide it.", "context/1": "We'II set the charges against the piles about three feet underwater, I should think and run the main wire downstream to the plunger.", "context/2": "...we'II have to do the job manually.", "context/3": "Since we don't know what time it'II cross tomorrow we'II have to do the job manually.", "context/4": "If not for the train, we could set a time fuse and be miles away.", "context/5": "If he knew we were here, it might boost his morale.", "context/6": "The Japanese seem to be enjoying it too.", "context/7": "They've got a British officer working on his knees.", "context/8": "Imagine being forced to build that in the condition they must be in.", "context/9": "Those poor devils down there."}
{"file_id": "lines-aaa", "context": "Well, then.", "response": "Honestly, Clipton, there are times when I don't understand you at all.", "context/0": "That's all true.", "context/1": "They feed better and they are no longer abused.", "context/2": "Yes, sir, but...", "context/3": "Are they a happier lot or aren't they?", "context/4": "Their condition has been improved?", "context/5": "Discipline has been restored?", "context/6": "You don't agree morale is high?", "context/7": "Take another look.", "context/8": "A good idea?", "context/9": "Yes, sir."}
{"file_id": "lines-aaa", "context": "Frankly, the consensus of opinion is that it's impossible.", "response": "But we'll certainly give it a go.", "context/0": "Can you finish the bridge in time?", "context/1": "One question.", "context/2": "And are there any other questions?", "context/3": "Thank you, Colonel Saito, for your kind attention.", "context/4": "I think that completes the agenda for this evening.", "context/5": "Yes, sir.", "context/6": "We'll try to surpass that, won't we?", "context/7": "I have already given the order.", "context/8": "That would also create a healthy competitive spirit.", "context/9": "I thought of setting it at a yard and a half so as not to overtire them but isn't it best to be the same as ours?"}
{"file_id": "lines-aaa", "context": "Also two others, Corporal Weaver and the American.", "response": "Jennings.", "context/0": "Killed, attempting to escape.", "context/1": "What?", "context/2": "Jennings is dead.", "context/3": "And Lieutenant Jennings....", "context/4": "They're still in detention.", "context/5": "Oh, they're not so good.", "context/6": "And the officers?", "context/7": "We scraped together a little meat and a coconut.", "context/8": "Fine, sir, fine.", "context/9": "How are the men?"}
{"file_id": "lines-aaa", "context": "May he rest in peace.", "response": "He found little of it while he was alive.", "context/0": "I don't mock the grave or the man.", "context/1": "No need to mock the grave.", "context/2": "Come off it.", "context/3": "What did he die for?", "context/4": "Valiant member of the King's Own or the Queen's Own or something who died of beri-beri in the year of our Lord, 1943 for the greater glory of....", "context/5": "Here lies Corporal Herbert Thomson serial number zero-one-two- three-four-five-six-seven.", "context/6": "Ah, yes.", "context/7": "Thomson.", "context/8": "I forgot who we just buried.", "context/9": "Here lies...."}
{"file_id": "lines-aaa", "context": "Like everything else in this jungle.", "response": "You might as well dump it!", "context/0": "It's wet, mildewed!", "context/1": "I'll tell you.", "context/2": "I can't get a strong signal.", "context/3": "It's taken an awful beating.", "context/4": "What's wrong with that thing?", "context/5": "Too much talk always spoils it.", "context/6": "No, that would spoil it.", "context/7": "I'll teach you to say that in Siamese.", "context/8": "What's a girl like you doing in a place like this?", "context/9": "She'll take the leeches off your back."}
{"file_id": "lines-aaa", "context": "Now you want me to go back?", "response": "Don't be ridiculous.", "context/0": "My escape was a miracle.", "context/1": "Major, I just got out of there.", "context/2": "Frankly, yes.", "context/3": "You mean to tell me you brought me here to ask me this?", "context/4": "I know under the circumstances it's a bit much... but you do have a unique knowledge for our purpose... and we'd love to have you with us.", "context/5": "Come again?", "context/6": "How would you feel about going back?", "context/7": "There is only one question, actually.", "context/8": "I am sorry.", "context/9": "Yes, of course."}
{"file_id": "lines-aaa", "context": "If this were your bridge how would you get it under way?", "response": "Get it under way, sir?", "context/0": "Yes, sir, half a dozen of them in Madras, Bengal...", "context/1": "Ever built a bridge over a stream like the Kwai?", "context/2": "Yes, sir?", "context/3": "I say, Reeves?", "context/4": "We must put a stop to these demonstrations.", "context/5": "No, sir.", "context/6": "It may be funny to you, but it's not military behavior.", "context/7": "Stop making those faces.", "context/8": "Have you a nervous affliction?", "context/9": "Oh, yes, sir."}
{"file_id": "lines-aaa", "context": "Now, you will be reasonable.", "response": "You will order your officers to work.", "context/0": "Looks like he doesn't want any witnesses.", "context/1": "What's he up to?", "context/2": "\"C\" Company, by the right.", "context/3": "Quick march, eyes right.", "context/4": "Eyes right.", "context/5": "Eyes front.", "context/6": "Eyes right.", "context/7": "\"A\" Company, by the right, quick march.", "context/8": "Left turn!", "context/9": "Move to the left in columnar route."}
{"file_id": "lines-aaa", "context": "To the king.", "response": "And you're in business.", "context/0": "Well done.", "context/1": "I congratulate you.", "context/2": "Here in the wilderness you have turned defeat into victory.", "context/3": "That, and more.", "context/4": "You have survived with honour.", "context/5": "What you have done should be and I think will be an example to all our countrymen, soldier and civilian alike.", "context/6": "But one day, in a week, a month, a year on that day when, God willing, we all return to our homes again you're going to feel very proud of what you have achieved here in the face of great adversity.", "context/7": "It's a very natural reaction.", "context/8": "That's quite understandable.", "context/9": "Now that your work here is finished I suppose many of you feel somewhat let down."}
{"file_id": "lines-aaa", "context": "I put two slugs in his big fat belly.", "response": "Him and the other two.", "context/0": "He's not laughing now.", "context/1": "Real loud.", "context/2": "And he was laughing.", "context/3": "They were coming up the steps.", "context/4": "That's the way it has to be.", "context/5": "Then we're going back to Chicago.", "context/6": "I'm staying with you.", "context/7": "I don't care what you do.", "context/8": "I'm gonna be moving fast.", "context/9": "I'm gonna rub this guy."}
{"file_id": "lines-aaa", "context": "Let's go and see.", "response": "What's holding them up?", "context/0": "I don't know.", "context/1": "What was that noise?", "context/2": "Come on.", "context/3": "We need a good strategy.", "context/4": "I'm not sure how many men are keeping watch.", "context/5": "We have to rescue your brother.", "context/6": "Yes.", "context/7": "Are you feeling all right?", "context/8": "I've never been so close to death.", "context/9": "Thank you, Pepe."}
{"file_id": "lines-aaa", "context": "No, but it won't take long to guess.", "response": "Oh, Emmett, please marry me.", "context/0": "You haven't told the others yet, have you?", "context/1": "I think I'm losing my mind.", "context/2": "I can't stand it any longer.", "context/3": "Let's not start that again.", "context/4": "Emmett, you've got to help me.", "context/5": "Just a little touch of sun.", "context/6": "You'll be all right.", "context/7": "Sit here.", "context/8": "You better rest for a while.", "context/9": "Move!"}
{"file_id": "lines-aaa", "context": "We could sure use three more guns.", "response": "Hey, where d'you get that horse?", "context/0": "Glad you're here.", "context/1": "It's no joke.", "context/2": "Don't josh.", "context/3": "That's a nasty word.", "context/4": "Indians?", "context/5": "You're just in time for a little Indian attack.", "context/6": "Correct.", "context/7": "Looks like we're at the right place at the right time.", "context/8": "You heard, boys.", "context/9": "Well, welcome, men."}
{"file_id": "lines-aaa", "context": "Look, men, I appreciate what you're trying to do, but you'll get me hung.", "response": "Clear out before I drive you out.", "context/0": "Hold it, Lacey.", "context/1": "Now we've been introduced, let's get out of here.", "context/2": "Incidentally, six of the best marksmen you ever saw.", "context/3": "I'd like you to meet Ogden, Conover, Sergeant Lacey, Melavan and Corporal Martin.", "context/4": "Colonel, this is that phantom petticoat army.", "context/5": "This ain't no bugle.", "context/6": "Stand easy.", "context/7": "We've come for the Lieutenant.", "context/8": "What's all this?", "context/9": "Up on your feet, everyone!"}
{"file_id": "lines-aaa", "context": "Any time you are.", "response": "The cab's stopping.", "context/0": "Mrs. Granger ready?", "context/1": "No, he's going east.", "context/2": "If that cab turns west, it could be trouble.", "context/3": "That's a bad intersection.", "context/4": "Frank, don't lose him if he turns on Santa Monica.", "context/5": "Stay with him.", "context/6": "The cab is in the left lane.", "context/7": "We're heading south on Roxbury.", "context/8": "Come in, partner.", "context/9": "Hello, Drake."}
{"file_id": "lines-aaa", "context": "I'm Jason Beckmeyer.", "response": "You called my office this morning.", "context/0": "Yes?", "context/1": "Miss Ansel.", "context/2": "I'd be happy to oblige.", "context/3": "But if you'd care to see a duplicate of the receipt I gave her,", "context/4": "All right, I won't tell you.", "context/5": "Don't tell me she turned the money over to you.", "context/6": "What do you suppose she wanted?", "context/7": "Miss Norge was in yesterday afternoon.", "context/8": "But there's just one teeny thing wrong with that theory, Mr. Mason.", "context/9": "Yeah."}
{"file_id": "lines-aaa", "context": "He said ideas came into his hands.", "response": "He must have been insane.", "context/0": "Did you hear what he said about his hands?", "context/1": "Yes, his hands.", "context/2": "His hands were like iron.", "context/3": "I can't believe it.", "context/4": "The sergeant.", "context/5": "It's a good thing we got the constable here in time.", "context/6": "We were following as close as we dared.", "context/7": "I know.", "context/8": "I thought I was done for, for a moment.", "context/9": "I never saw anything so quick or anyone so strong."}
